cdasws/__init__.py
cdasws/__main__.py
cdasws/cdasws.py
cdasws/datarepresentation.py
cdasws/datarequest.py
cdasws/timeinterval.py
cdasws-1.8.11.dist-info/licenses/LICENSE
tests/__init__.py
tests/test_cdasws.py
cdasws-1.8.11.dist-info/METADATA
cdasws-1.8.11.dist-info/WHEEL
cdasws-1.8.11.dist-info/top_level.txt
cdasws-1.8.11.dist-info/RECORD
