Metadata-Version: 2.4
Name: cdasws
Version: 1.8.11
Summary: NASA's Coordinated Data Analysis System Web Service Client Library
Home-page: https://cdaweb.gsfc.nasa.gov/WebServices/REST
Author: Bernie Harris
Author-email: NASA-SPDF-Support@nasa.onmicrosoft.com
License: NOSA
Keywords: heliophysics,coordinated data analysis,multi-mission,multi-instrument,space physics,spdf,cdaweb
Classifier: Development Status :: 5 - Production/Stable
Classifier: Environment :: Console
Classifier: Environment :: Web Environment
Classifier: Intended Audience :: End Users/Desktop
Classifier: Intended Audience :: Developers
Classifier: Intended Audience :: System Administrators
Classifier: License :: OSI Approved :: NASA Open Source Agreement v1.3 (NASA-1.3)
Classifier: Operating System :: OS Independent
Classifier: Programming Language :: Python
Classifier: Topic :: Scientific/Engineering :: Physics
Classifier: Topic :: Software Development :: Libraries :: Python Modules
License-File: LICENSE
Requires-Dist: python-dateutil>=2.8.0
Requires-Dist: requests>=2.20
Requires-Dist: urllib3>=1.24.1
Provides-Extra: spdm
Requires-Dist: spacepy>=0.5.0; extra == "spdm"
Provides-Extra: xarray
Requires-Dist: cdflib>=0.4.4; extra == "xarray"
Provides-Extra: cache
Requires-Dist: requests-cache>=1.2.1; extra == "cache"
Dynamic: author
Dynamic: author-email
Dynamic: classifier
Dynamic: description
Dynamic: description-content-type
Dynamic: home-page
Dynamic: keywords
Dynamic: license
Dynamic: license-file
Dynamic: provides-extra
Dynamic: requires-dist
Dynamic: summary
